mc_wiki_fetch_mcp/__init__.py
mc_wiki_fetch_mcp-0.3.0.dist-info/METADATA
mc_wiki_fetch_mcp-0.3.0.dist-info/WHEEL
mc_wiki_fetch_mcp-0.3.0.dist-info/entry_points.txt
mc_wiki_fetch_mcp-0.3.0.dist-info/licenses/LICENSE
mc_wiki_fetch_mcp-0.3.0.dist-info/RECORD
