Metadata-Version: 2.4
Name: mc-wiki-fetch-mcp
Version: 0.3.0
Summary: A MCP-based Minecraft Wiki backend server providing convenient access to Minecraft Wiki content via stdio
Project-URL: Homepage, https://github.com/rice-awa/mc-wiki-mcp-pypi
Project-URL: Repository, https://github.com/rice-awa/mc-wiki-mcp-pypi
Project-URL: Issues, https://github.com/rice-awa/mc-wiki-mcp-pypi/issues
Project-URL: Documentation, https://github.com/rice-awa/mc-wiki-mcp-pypi/blob/main/README.md
Author-email: rice_awa <riceawa@rice-awa.top>
License-File: LICENSE
Keywords: api,mcp,minecraft,server,wiki
Classifier: Development Status :: 4 - Beta
Classifier: Intended Audience :: Developers
Classifier: License :: OSI Approved :: MIT License
Classifier: Programming Language :: Python :: 3
Classifier: Programming Language :: Python :: 3.10
Classifier: Programming Language :: Python :: 3.11
Classifier: Programming Language :: Python :: 3.12
Classifier: Programming Language :: Python :: 3.13
Classifier: Topic :: Games/Entertainment
Classifier: Topic :: Internet :: WWW/HTTP :: HTTP Servers
Requires-Python: >=3.10
Requires-Dist: aiohttp>=3.8.0
Requires-Dist: fastmcp>=0.1.0
Requires-Dist: mcp>=1.12.3
